<?xml version="1.0" encoding="utf-8"?>
<helpItems schema="maml" xmlns="http://msh">
  <command:command xmlns:maml="http://schemas.microsoft.com/maml/2004/10" xmlns:command="http://schemas.microsoft.com/maml/dev/command/2004/10" xmlns:dev="http://schemas.microsoft.com/maml/dev/2004/10" xmlns:MSHelp="http://msdn.microsoft.com/mshelp">
    <command:details>
      <command:name>Get-RunInfo</command:name>
      <command:verb>Get</command:verb>
      <command:noun>RunInfo</command:noun>
      <maml:description>
        <maml:para>Get PowerShell session information</maml:para>
      </maml:description>
    </command:details>
    <maml:description>
      <maml:para>Get Powershell current session information</maml:para>
    </maml:description>
    <command:syntax>
      <command:syntaxItem>
        <maml:name>Get-RunInfo</maml:name>
        <command:parameter required="false" variableLength="true" globbing="false" pipelineInput="False" position="named" aliases="none">
          <maml:name>AsString</maml:name>
          <maml:Description>
            <maml:para>{{ Fill AsString Description }}</maml:para>
          </maml:Description>
          <dev:type>
            <maml:name>SwitchParameter</maml:name>
            <maml:uri />
          </dev:type>
          <dev:defaultValue>False</dev:defaultValue>
        </command:parameter>
      </command:syntaxItem>
    </command:syntax>
    <command:parameters>
      <command:parameter required="false" variableLength="true" globbing="false" pipelineInput="False" position="named" aliases="none">
        <maml:name>AsString</maml:name>
        <maml:Description>
          <maml:para>{{ Fill AsString Description }}</maml:para>
        </maml:Description>
        <command:parameterValue required="false" variableLength="false">SwitchParameter</command:parameterValue>
        <dev:type>
          <maml:name>SwitchParameter</maml:name>
          <maml:uri />
        </dev:type>
        <dev:defaultValue>False</dev:defaultValue>
      </command:parameter>
    </command:parameters>
    <command:inputTypes />
    <command:returnValues />
    <maml:alertSet>
      <maml:alert>
        <maml:para></maml:para>
      </maml:alert>
    </maml:alertSet>
    <command:examples>
      <command:example>
        <maml:title>-------------------------- EXEMPLE 1 --------------------------</maml:title>
        <dev:code>Get-RunInfo</dev:code>
        <dev:remarks>
          <maml:para>User            : XPS\Xeph Elevated        : False Computername    : XPS OperatingSystem : Microsoft Windows 10 Professionnel [64 bits] OSVersion       : 10.0.18363 PSVersion       : 5.1.18362.145 Edition         : Desktop PSHost          : Visual Studio Code Host WSMan           : 3.0 ExecutionPolicy : RemoteSigned Culture         : fr-FR</maml:para>
        </dev:remarks>
      </command:example>
    </command:examples>
    <command:relatedLinks />
  </command:command>
  <command:command xmlns:maml="http://schemas.microsoft.com/maml/2004/10" xmlns:command="http://schemas.microsoft.com/maml/dev/command/2004/10" xmlns:dev="http://schemas.microsoft.com/maml/dev/2004/10" xmlns:MSHelp="http://msdn.microsoft.com/mshelp">
    <command:details>
      <command:name>Out-HTML</command:name>
      <command:verb>Out</command:verb>
      <command:noun>HTML</command:noun>
      <maml:description>
        <maml:para>Create a HTML Table with object send by the pipeline</maml:para>
      </maml:description>
    </command:details>
    <maml:description>
      <maml:para>Create a HTML Table with object send by the pipeline.  2 CSS Theme with colored line by string match</maml:para>
    </maml:description>
    <command:syntax>
      <command:syntaxItem>
        <maml:name>Out-HTML</maml:name>
        <command:parameter required="false" variableLength="true" globbing="false" pipelineInput="False" position="1" aliases="none">
          <maml:name>Path</maml:name>
          <maml:Description>
            <maml:para>{{ Fill Path Description }}</maml:para>
          </maml:Description>
          <command:parameterValue required="true" variableLength="false">String</command:parameterValue>
          <dev:type>
            <maml:name>String</maml:name>
            <maml:uri />
          </dev:type>
          <dev:defaultValue>"$Home\Desktop\report$(Get-Date -format yyyy-MM-dd-HH-mm-ss).html"</dev:defaultValue>
        </command:parameter>
        <command:parameter required="false" variableLength="true" globbing="false" pipelineInput="False" position="2" aliases="none">
          <maml:name>Title</maml:name>
          <maml:Description>
            <maml:para>{{ Fill Title Description }}</maml:para>
          </maml:Description>
          <command:parameterValue required="true" variableLength="false">String</command:parameterValue>
          <dev:type>
            <maml:name>String</maml:name>
            <maml:uri />
          </dev:type>
          <dev:defaultValue>PowerShell Output</dev:defaultValue>
        </command:parameter>
        <command:parameter required="false" variableLength="true" globbing="false" pipelineInput="False" position="3" aliases="none">
          <maml:name>ErrorMatch</maml:name>
          <maml:Description>
            <maml:para>Color Line in red where this string is present . Add counter of error on top of the table</maml:para>
          </maml:Description>
          <command:parameterValue required="true" variableLength="false">String</command:parameterValue>
          <dev:type>
            <maml:name>String</maml:name>
            <maml:uri />
          </dev:type>
          <dev:defaultValue>None</dev:defaultValue>
        </command:parameter>
        <command:parameter required="false" variableLength="true" globbing="false" pipelineInput="False" position="4" aliases="none">
          <maml:name>WarningMatch</maml:name>
          <maml:Description>
            <maml:para>{{ Fill WarningMatch Description }}</maml:para>
          </maml:Description>
          <command:parameterValue required="true" variableLength="false">String</command:parameterValue>
          <dev:type>
            <maml:name>String</maml:name>
            <maml:uri />
          </dev:type>
          <dev:defaultValue>None</dev:defaultValue>
        </command:parameter>
        <command:parameter required="false" variableLength="true" globbing="false" pipelineInput="False" position="5" aliases="none">
          <maml:name>SuccessMatch</maml:name>
          <maml:Description>
            <maml:para>Color Line in green where this string is present . Add counter of success on top of the table</maml:para>
          </maml:Description>
          <command:parameterValue required="true" variableLength="false">String</command:parameterValue>
          <dev:type>
            <maml:name>String</maml:name>
            <maml:uri />
          </dev:type>
          <dev:defaultValue>None</dev:defaultValue>
        </command:parameter>
        <command:parameter required="false" variableLength="true" globbing="false" pipelineInput="False" position="6" aliases="none">
          <maml:name>Template</maml:name>
          <maml:Description>
            <maml:para>{{ Fill Template Description }}</maml:para>
          </maml:Description>
          <command:parameterValue required="true" variableLength="false">String</command:parameterValue>
          <dev:type>
            <maml:name>String</maml:name>
            <maml:uri />
          </dev:type>
          <dev:defaultValue>Light</dev:defaultValue>
        </command:parameter>
        <command:parameter required="false" variableLength="true" globbing="false" pipelineInput="False" position="named" aliases="none">
          <maml:name>Open</maml:name>
          <maml:Description>
            <maml:para>{{ Fill Open Description }}</maml:para>
          </maml:Description>
          <dev:type>
            <maml:name>SwitchParameter</maml:name>
            <maml:uri />
          </dev:type>
          <dev:defaultValue>False</dev:defaultValue>
        </command:parameter>
        <command:parameter required="false" variableLength="true" globbing="false" pipelineInput="False" position="named" aliases="none">
          <maml:name>Search</maml:name>
          <maml:Description>
            <maml:para>Add a search field for dynamic search in the file</maml:para>
          </maml:Description>
          <dev:type>
            <maml:name>SwitchParameter</maml:name>
            <maml:uri />
          </dev:type>
          <dev:defaultValue>False</dev:defaultValue>
        </command:parameter>
      </command:syntaxItem>
    </command:syntax>
    <command:parameters>
      <command:parameter required="false" variableLength="true" globbing="false" pipelineInput="False" position="1" aliases="none">
        <maml:name>Path</maml:name>
        <maml:Description>
          <maml:para>{{ Fill Path Description }}</maml:para>
        </maml:Description>
        <command:parameterValue required="true" variableLength="false">String</command:parameterValue>
        <dev:type>
          <maml:name>String</maml:name>
          <maml:uri />
        </dev:type>
        <dev:defaultValue>"$Home\Desktop\report$(Get-Date -format yyyy-MM-dd-HH-mm-ss).html"</dev:defaultValue>
      </command:parameter>
      <command:parameter required="false" variableLength="true" globbing="false" pipelineInput="False" position="2" aliases="none">
        <maml:name>Title</maml:name>
        <maml:Description>
          <maml:para>{{ Fill Title Description }}</maml:para>
        </maml:Description>
        <command:parameterValue required="true" variableLength="false">String</command:parameterValue>
        <dev:type>
          <maml:name>String</maml:name>
          <maml:uri />
        </dev:type>
        <dev:defaultValue>PowerShell Output</dev:defaultValue>
      </command:parameter>
      <command:parameter required="false" variableLength="true" globbing="false" pipelineInput="False" position="3" aliases="none">
        <maml:name>ErrorMatch</maml:name>
        <maml:Description>
          <maml:para>Color Line in red where this string is present . Add counter of error on top of the table</maml:para>
        </maml:Description>
        <command:parameterValue required="true" variableLength="false">String</command:parameterValue>
        <dev:type>
          <maml:name>String</maml:name>
          <maml:uri />
        </dev:type>
        <dev:defaultValue>None</dev:defaultValue>
      </command:parameter>
      <command:parameter required="false" variableLength="true" globbing="false" pipelineInput="False" position="4" aliases="none">
        <maml:name>WarningMatch</maml:name>
        <maml:Description>
          <maml:para>{{ Fill WarningMatch Description }}</maml:para>
        </maml:Description>
        <command:parameterValue required="true" variableLength="false">String</command:parameterValue>
        <dev:type>
          <maml:name>String</maml:name>
          <maml:uri />
        </dev:type>
        <dev:defaultValue>None</dev:defaultValue>
      </command:parameter>
      <command:parameter required="false" variableLength="true" globbing="false" pipelineInput="False" position="5" aliases="none">
        <maml:name>SuccessMatch</maml:name>
        <maml:Description>
          <maml:para>Color Line in green where this string is present . Add counter of success on top of the table</maml:para>
        </maml:Description>
        <command:parameterValue required="true" variableLength="false">String</command:parameterValue>
        <dev:type>
          <maml:name>String</maml:name>
          <maml:uri />
        </dev:type>
        <dev:defaultValue>None</dev:defaultValue>
      </command:parameter>
      <command:parameter required="false" variableLength="true" globbing="false" pipelineInput="False" position="6" aliases="none">
        <maml:name>Template</maml:name>
        <maml:Description>
          <maml:para>{{ Fill Template Description }}</maml:para>
        </maml:Description>
        <command:parameterValue required="true" variableLength="false">String</command:parameterValue>
        <dev:type>
          <maml:name>String</maml:name>
          <maml:uri />
        </dev:type>
        <dev:defaultValue>Light</dev:defaultValue>
      </command:parameter>
      <command:parameter required="false" variableLength="true" globbing="false" pipelineInput="False" position="named" aliases="none">
        <maml:name>Open</maml:name>
        <maml:Description>
          <maml:para>{{ Fill Open Description }}</maml:para>
        </maml:Description>
        <command:parameterValue required="false" variableLength="false">SwitchParameter</command:parameterValue>
        <dev:type>
          <maml:name>SwitchParameter</maml:name>
          <maml:uri />
        </dev:type>
        <dev:defaultValue>False</dev:defaultValue>
      </command:parameter>
      <command:parameter required="false" variableLength="true" globbing="false" pipelineInput="False" position="named" aliases="none">
        <maml:name>Search</maml:name>
        <maml:Description>
          <maml:para>Add a search field for dynamic search in the file</maml:para>
        </maml:Description>
        <command:parameterValue required="false" variableLength="false">SwitchParameter</command:parameterValue>
        <dev:type>
          <maml:name>SwitchParameter</maml:name>
          <maml:uri />
        </dev:type>
        <dev:defaultValue>False</dev:defaultValue>
      </command:parameter>
    </command:parameters>
    <command:inputTypes />
    <command:returnValues />
    <maml:alertSet>
      <maml:alert>
        <maml:para></maml:para>
      </maml:alert>
    </maml:alertSet>
    <command:examples>
      <command:example>
        <maml:title>-------------------------- EXEMPLE 1 --------------------------</maml:title>
        <dev:code>Get-Service | Select Name,Status | Out-HTML -ErrorMatch "Stopped" -SuccessMatch "Running" -Title "Services" -Template Dark -Open -Search</dev:code>
        <dev:remarks>
          <maml:para></maml:para>
        </dev:remarks>
      </command:example>
    </command:examples>
    <command:relatedLinks />
  </command:command>
  <command:command xmlns:maml="http://schemas.microsoft.com/maml/2004/10" xmlns:command="http://schemas.microsoft.com/maml/dev/command/2004/10" xmlns:dev="http://schemas.microsoft.com/maml/dev/2004/10" xmlns:MSHelp="http://msdn.microsoft.com/mshelp">
    <command:details>
      <command:name>Show-DynamicMenu</command:name>
      <command:verb>Show</command:verb>
      <command:noun>DynamicMenu</command:noun>
      <maml:description>
        <maml:para>Create a CLI Menu</maml:para>
      </maml:description>
    </command:details>
    <maml:description>
      <maml:para>Create a CLI Menu</maml:para>
    </maml:description>
    <command:syntax>
      <command:syntaxItem>
        <maml:name>Show-DynamicMenu</maml:name>
        <command:parameter required="true" variableLength="true" globbing="false" pipelineInput="False" position="1" aliases="none">
          <maml:name>menuTitle</maml:name>
          <maml:Description>
            <maml:para>{{ Fill menuTitle Description }}</maml:para>
          </maml:Description>
          <command:parameterValue required="true" variableLength="false">String</command:parameterValue>
          <dev:type>
            <maml:name>String</maml:name>
            <maml:uri />
          </dev:type>
          <dev:defaultValue>None</dev:defaultValue>
        </command:parameter>
        <command:parameter required="true" variableLength="true" globbing="false" pipelineInput="False" position="2" aliases="none">
          <maml:name>menuKeys</maml:name>
          <maml:Description>
            <maml:para>{{ Fill menuKeys Description }}</maml:para>
          </maml:Description>
          <command:parameterValue required="true" variableLength="false">Array</command:parameterValue>
          <dev:type>
            <maml:name>Array</maml:name>
            <maml:uri />
          </dev:type>
          <dev:defaultValue>None</dev:defaultValue>
        </command:parameter>
        <command:parameter required="true" variableLength="true" globbing="false" pipelineInput="False" position="3" aliases="none">
          <maml:name>menuOptions</maml:name>
          <maml:Description>
            <maml:para>{{ Fill menuOptions Description }}</maml:para>
          </maml:Description>
          <command:parameterValue required="true" variableLength="false">Array</command:parameterValue>
          <dev:type>
            <maml:name>Array</maml:name>
            <maml:uri />
          </dev:type>
          <dev:defaultValue>None</dev:defaultValue>
        </command:parameter>
        <command:parameter required="true" variableLength="true" globbing="false" pipelineInput="False" position="4" aliases="none">
          <maml:name>menuActions</maml:name>
          <maml:Description>
            <maml:para>{{ Fill menuActions Description }}</maml:para>
          </maml:Description>
          <command:parameterValue required="true" variableLength="false">Array</command:parameterValue>
          <dev:type>
            <maml:name>Array</maml:name>
            <maml:uri />
          </dev:type>
          <dev:defaultValue>None</dev:defaultValue>
        </command:parameter>
      </command:syntaxItem>
    </command:syntax>
    <command:parameters>
      <command:parameter required="true" variableLength="true" globbing="false" pipelineInput="False" position="1" aliases="none">
        <maml:name>menuTitle</maml:name>
        <maml:Description>
          <maml:para>{{ Fill menuTitle Description }}</maml:para>
        </maml:Description>
        <command:parameterValue required="true" variableLength="false">String</command:parameterValue>
        <dev:type>
          <maml:name>String</maml:name>
          <maml:uri />
        </dev:type>
        <dev:defaultValue>None</dev:defaultValue>
      </command:parameter>
      <command:parameter required="true" variableLength="true" globbing="false" pipelineInput="False" position="2" aliases="none">
        <maml:name>menuKeys</maml:name>
        <maml:Description>
          <maml:para>{{ Fill menuKeys Description }}</maml:para>
        </maml:Description>
        <command:parameterValue required="true" variableLength="false">Array</command:parameterValue>
        <dev:type>
          <maml:name>Array</maml:name>
          <maml:uri />
        </dev:type>
        <dev:defaultValue>None</dev:defaultValue>
      </command:parameter>
      <command:parameter required="true" variableLength="true" globbing="false" pipelineInput="False" position="3" aliases="none">
        <maml:name>menuOptions</maml:name>
        <maml:Description>
          <maml:para>{{ Fill menuOptions Description }}</maml:para>
        </maml:Description>
        <command:parameterValue required="true" variableLength="false">Array</command:parameterValue>
        <dev:type>
          <maml:name>Array</maml:name>
          <maml:uri />
        </dev:type>
        <dev:defaultValue>None</dev:defaultValue>
      </command:parameter>
      <command:parameter required="true" variableLength="true" globbing="false" pipelineInput="False" position="4" aliases="none">
        <maml:name>menuActions</maml:name>
        <maml:Description>
          <maml:para>{{ Fill menuActions Description }}</maml:para>
        </maml:Description>
        <command:parameterValue required="true" variableLength="false">Array</command:parameterValue>
        <dev:type>
          <maml:name>Array</maml:name>
          <maml:uri />
        </dev:type>
        <dev:defaultValue>None</dev:defaultValue>
      </command:parameter>
    </command:parameters>
    <command:inputTypes />
    <command:returnValues />
    <maml:alertSet>
      <maml:alert>
        <maml:para></maml:para>
      </maml:alert>
    </maml:alertSet>
    <command:examples>
      <command:example>
        <maml:title>-------------------------- EXEMPLE 1 --------------------------</maml:title>
        <dev:code>$Menu = @{</dev:code>
        <dev:remarks>
          <maml:para>MenuTitle = "Menu"     MenuKeys = @(1,2,3,4)     menuOptions = @("Options1","Options2","Options3","Options4")     menuActions = @('Write-Host "You Choose Option1 !"','Write-Host "You Choose Option2 !"','Write-Host "You Choose Option3 !"','Write-Host "You Choose Option4 !"') }</maml:para>
          <maml:para>Show-DynamicMenu @Menu</maml:para>
        </dev:remarks>
      </command:example>
    </command:examples>
    <command:relatedLinks />
  </command:command>
  <command:command xmlns:maml="http://schemas.microsoft.com/maml/2004/10" xmlns:command="http://schemas.microsoft.com/maml/dev/command/2004/10" xmlns:dev="http://schemas.microsoft.com/maml/dev/2004/10" xmlns:MSHelp="http://msdn.microsoft.com/mshelp">
    <command:details>
      <command:name>Write-ColorLog</command:name>
      <command:verb>Write</command:verb>
      <command:noun>ColorLog</command:noun>
      <maml:description>
        <maml:para>{{ Fill in the Synopsis }}</maml:para>
      </maml:description>
    </command:details>
    <maml:description>
      <maml:para>{{ Fill in the Description }}</maml:para>
    </maml:description>
    <command:syntax>
      <command:syntaxItem>
        <maml:name>Write-ColorLog</maml:name>
        <command:parameter required="false" variableLength="true" globbing="false" pipelineInput="False" position="nommé" aliases="none">
          <maml:name>Color</maml:name>
          <maml:Description>
            <maml:para>{{ Fill Color Description }}</maml:para>
          </maml:Description>
          <command:parameterValueGroup>
            <command:parameterValue required="false" command:variableLength="false">Black</command:parameterValue>
            <command:parameterValue required="false" command:variableLength="false">DarkBlue</command:parameterValue>
            <command:parameterValue required="false" command:variableLength="false">DarkGreen</command:parameterValue>
            <command:parameterValue required="false" command:variableLength="false">DarkCyan</command:parameterValue>
            <command:parameterValue required="false" command:variableLength="false">DarkRed</command:parameterValue>
            <command:parameterValue required="false" command:variableLength="false">DarkMagenta</command:parameterValue>
            <command:parameterValue required="false" command:variableLength="false">DarkYellow</command:parameterValue>
            <command:parameterValue required="false" command:variableLength="false">Gray</command:parameterValue>
            <command:parameterValue required="false" command:variableLength="false">DarkGray</command:parameterValue>
            <command:parameterValue required="false" command:variableLength="false">Blue</command:parameterValue>
            <command:parameterValue required="false" command:variableLength="false">Green</command:parameterValue>
            <command:parameterValue required="false" command:variableLength="false">Cyan</command:parameterValue>
            <command:parameterValue required="false" command:variableLength="false">Red</command:parameterValue>
            <command:parameterValue required="false" command:variableLength="false">Magenta</command:parameterValue>
            <command:parameterValue required="false" command:variableLength="false">Yellow</command:parameterValue>
            <command:parameterValue required="false" command:variableLength="false">White</command:parameterValue>
          </command:parameterValueGroup>
          <command:parameterValue required="true" variableLength="false">ConsoleColor[]</command:parameterValue>
          <dev:type>
            <maml:name>ConsoleColor[]</maml:name>
            <maml:uri />
          </dev:type>
          <dev:defaultValue>None</dev:defaultValue>
        </command:parameter>
        <command:parameter required="true" variableLength="true" globbing="false" pipelineInput="True (ByValue)" position="nommé" aliases="none">
          <maml:name>EndLog</maml:name>
          <maml:Description>
            <maml:para>{{ Fill EndLog Description }}</maml:para>
          </maml:Description>
          <dev:type>
            <maml:name>SwitchParameter</maml:name>
            <maml:uri />
          </dev:type>
          <dev:defaultValue>False</dev:defaultValue>
        </command:parameter>
        <command:parameter required="false" variableLength="true" globbing="false" pipelineInput="False" position="nommé" aliases="none">
          <maml:name>LinesAfter</maml:name>
          <maml:Description>
            <maml:para>{{ Fill LinesAfter Description }}</maml:para>
          </maml:Description>
          <command:parameterValue required="true" variableLength="false">Int32</command:parameterValue>
          <dev:type>
            <maml:name>Int32</maml:name>
            <maml:uri />
          </dev:type>
          <dev:defaultValue>None</dev:defaultValue>
        </command:parameter>
        <command:parameter required="false" variableLength="true" globbing="false" pipelineInput="False" position="nommé" aliases="none">
          <maml:name>LinesBefore</maml:name>
          <maml:Description>
            <maml:para>{{ Fill LinesBefore Description }}</maml:para>
          </maml:Description>
          <command:parameterValue required="true" variableLength="false">Int32</command:parameterValue>
          <dev:type>
            <maml:name>Int32</maml:name>
            <maml:uri />
          </dev:type>
          <dev:defaultValue>None</dev:defaultValue>
        </command:parameter>
        <command:parameter required="false" variableLength="true" globbing="false" pipelineInput="True (ByValue)" position="nommé" aliases="none">
          <maml:name>LogFile</maml:name>
          <maml:Description>
            <maml:para>{{ Fill LogFile Description }}</maml:para>
          </maml:Description>
          <command:parameterValue required="true" variableLength="false">String</command:parameterValue>
          <dev:type>
            <maml:name>String</maml:name>
            <maml:uri />
          </dev:type>
          <dev:defaultValue>None</dev:defaultValue>
        </command:parameter>
        <command:parameter required="false" variableLength="true" globbing="false" pipelineInput="False" position="nommé" aliases="none">
          <maml:name>NoNewLine</maml:name>
          <maml:Description>
            <maml:para>{{ Fill NoNewLine Description }}</maml:para>
          </maml:Description>
          <dev:type>
            <maml:name>SwitchParameter</maml:name>
            <maml:uri />
          </dev:type>
          <dev:defaultValue>False</dev:defaultValue>
        </command:parameter>
        <command:parameter required="false" variableLength="true" globbing="false" pipelineInput="False" position="nommé" aliases="none">
          <maml:name>ShowTime</maml:name>
          <maml:Description>
            <maml:para>{{ Fill ShowTime Description }}</maml:para>
          </maml:Description>
          <dev:type>
            <maml:name>SwitchParameter</maml:name>
            <maml:uri />
          </dev:type>
          <dev:defaultValue>False</dev:defaultValue>
        </command:parameter>
        <command:parameter required="false" variableLength="true" globbing="false" pipelineInput="False" position="nommé" aliases="none">
          <maml:name>StartTab</maml:name>
          <maml:Description>
            <maml:para>{{ Fill StartTab Description }}</maml:para>
          </maml:Description>
          <command:parameterValue required="true" variableLength="false">Int32</command:parameterValue>
          <dev:type>
            <maml:name>Int32</maml:name>
            <maml:uri />
          </dev:type>
          <dev:defaultValue>None</dev:defaultValue>
        </command:parameter>
      </command:syntaxItem>
      <command:syntaxItem>
        <maml:name>Write-ColorLog</maml:name>
        <command:parameter required="false" variableLength="true" globbing="false" pipelineInput="False" position="nommé" aliases="none">
          <maml:name>Color</maml:name>
          <maml:Description>
            <maml:para>{{ Fill Color Description }}</maml:para>
          </maml:Description>
          <command:parameterValueGroup>
            <command:parameterValue required="false" command:variableLength="false">Black</command:parameterValue>
            <command:parameterValue required="false" command:variableLength="false">DarkBlue</command:parameterValue>
            <command:parameterValue required="false" command:variableLength="false">DarkGreen</command:parameterValue>
            <command:parameterValue required="false" command:variableLength="false">DarkCyan</command:parameterValue>
            <command:parameterValue required="false" command:variableLength="false">DarkRed</command:parameterValue>
            <command:parameterValue required="false" command:variableLength="false">DarkMagenta</command:parameterValue>
            <command:parameterValue required="false" command:variableLength="false">DarkYellow</command:parameterValue>
            <command:parameterValue required="false" command:variableLength="false">Gray</command:parameterValue>
            <command:parameterValue required="false" command:variableLength="false">DarkGray</command:parameterValue>
            <command:parameterValue required="false" command:variableLength="false">Blue</command:parameterValue>
            <command:parameterValue required="false" command:variableLength="false">Green</command:parameterValue>
            <command:parameterValue required="false" command:variableLength="false">Cyan</command:parameterValue>
            <command:parameterValue required="false" command:variableLength="false">Red</command:parameterValue>
            <command:parameterValue required="false" command:variableLength="false">Magenta</command:parameterValue>
            <command:parameterValue required="false" command:variableLength="false">Yellow</command:parameterValue>
            <command:parameterValue required="false" command:variableLength="false">White</command:parameterValue>
          </command:parameterValueGroup>
          <command:parameterValue required="true" variableLength="false">ConsoleColor[]</command:parameterValue>
          <dev:type>
            <maml:name>ConsoleColor[]</maml:name>
            <maml:uri />
          </dev:type>
          <dev:defaultValue>None</dev:defaultValue>
        </command:parameter>
        <command:parameter required="false" variableLength="true" globbing="false" pipelineInput="False" position="nommé" aliases="none">
          <maml:name>LinesAfter</maml:name>
          <maml:Description>
            <maml:para>{{ Fill LinesAfter Description }}</maml:para>
          </maml:Description>
          <command:parameterValue required="true" variableLength="false">Int32</command:parameterValue>
          <dev:type>
            <maml:name>Int32</maml:name>
            <maml:uri />
          </dev:type>
          <dev:defaultValue>None</dev:defaultValue>
        </command:parameter>
        <command:parameter required="false" variableLength="true" globbing="false" pipelineInput="False" position="nommé" aliases="none">
          <maml:name>LinesBefore</maml:name>
          <maml:Description>
            <maml:para>{{ Fill LinesBefore Description }}</maml:para>
          </maml:Description>
          <command:parameterValue required="true" variableLength="false">Int32</command:parameterValue>
          <dev:type>
            <maml:name>Int32</maml:name>
            <maml:uri />
          </dev:type>
          <dev:defaultValue>None</dev:defaultValue>
        </command:parameter>
        <command:parameter required="false" variableLength="true" globbing="false" pipelineInput="True (ByValue)" position="nommé" aliases="none">
          <maml:name>LogFile</maml:name>
          <maml:Description>
            <maml:para>{{ Fill LogFile Description }}</maml:para>
          </maml:Description>
          <command:parameterValue required="true" variableLength="false">String</command:parameterValue>
          <dev:type>
            <maml:name>String</maml:name>
            <maml:uri />
          </dev:type>
          <dev:defaultValue>None</dev:defaultValue>
        </command:parameter>
        <command:parameter required="false" variableLength="true" globbing="false" pipelineInput="False" position="nommé" aliases="none">
          <maml:name>NoNewLine</maml:name>
          <maml:Description>
            <maml:para>{{ Fill NoNewLine Description }}</maml:para>
          </maml:Description>
          <dev:type>
            <maml:name>SwitchParameter</maml:name>
            <maml:uri />
          </dev:type>
          <dev:defaultValue>False</dev:defaultValue>
        </command:parameter>
        <command:parameter required="false" variableLength="true" globbing="false" pipelineInput="False" position="nommé" aliases="none">
          <maml:name>ShowTime</maml:name>
          <maml:Description>
            <maml:para>{{ Fill ShowTime Description }}</maml:para>
          </maml:Description>
          <dev:type>
            <maml:name>SwitchParameter</maml:name>
            <maml:uri />
          </dev:type>
          <dev:defaultValue>False</dev:defaultValue>
        </command:parameter>
        <command:parameter required="true" variableLength="true" globbing="false" pipelineInput="True (ByValue)" position="nommé" aliases="none">
          <maml:name>StartLog</maml:name>
          <maml:Description>
            <maml:para>{{ Fill StartLog Description }}</maml:para>
          </maml:Description>
          <dev:type>
            <maml:name>SwitchParameter</maml:name>
            <maml:uri />
          </dev:type>
          <dev:defaultValue>False</dev:defaultValue>
        </command:parameter>
        <command:parameter required="false" variableLength="true" globbing="false" pipelineInput="False" position="nommé" aliases="none">
          <maml:name>StartTab</maml:name>
          <maml:Description>
            <maml:para>{{ Fill StartTab Description }}</maml:para>
          </maml:Description>
          <command:parameterValue required="true" variableLength="false">Int32</command:parameterValue>
          <dev:type>
            <maml:name>Int32</maml:name>
            <maml:uri />
          </dev:type>
          <dev:defaultValue>None</dev:defaultValue>
        </command:parameter>
      </command:syntaxItem>
      <command:syntaxItem>
        <maml:name>Write-ColorLog</maml:name>
        <command:parameter required="false" variableLength="true" globbing="false" pipelineInput="False" position="nommé" aliases="none">
          <maml:name>Color</maml:name>
          <maml:Description>
            <maml:para>{{ Fill Color Description }}</maml:para>
          </maml:Description>
          <command:parameterValueGroup>
            <command:parameterValue required="false" command:variableLength="false">Black</command:parameterValue>
            <command:parameterValue required="false" command:variableLength="false">DarkBlue</command:parameterValue>
            <command:parameterValue required="false" command:variableLength="false">DarkGreen</command:parameterValue>
            <command:parameterValue required="false" command:variableLength="false">DarkCyan</command:parameterValue>
            <command:parameterValue required="false" command:variableLength="false">DarkRed</command:parameterValue>
            <command:parameterValue required="false" command:variableLength="false">DarkMagenta</command:parameterValue>
            <command:parameterValue required="false" command:variableLength="false">DarkYellow</command:parameterValue>
            <command:parameterValue required="false" command:variableLength="false">Gray</command:parameterValue>
            <command:parameterValue required="false" command:variableLength="false">DarkGray</command:parameterValue>
            <command:parameterValue required="false" command:variableLength="false">Blue</command:parameterValue>
            <command:parameterValue required="false" command:variableLength="false">Green</command:parameterValue>
            <command:parameterValue required="false" command:variableLength="false">Cyan</command:parameterValue>
            <command:parameterValue required="false" command:variableLength="false">Red</command:parameterValue>
            <command:parameterValue required="false" command:variableLength="false">Magenta</command:parameterValue>
            <command:parameterValue required="false" command:variableLength="false">Yellow</command:parameterValue>
            <command:parameterValue required="false" command:variableLength="false">White</command:parameterValue>
          </command:parameterValueGroup>
          <command:parameterValue required="true" variableLength="false">ConsoleColor[]</command:parameterValue>
          <dev:type>
            <maml:name>ConsoleColor[]</maml:name>
            <maml:uri />
          </dev:type>
          <dev:defaultValue>None</dev:defaultValue>
        </command:parameter>
        <command:parameter required="false" variableLength="true" globbing="false" pipelineInput="False" position="nommé" aliases="none">
          <maml:name>LinesAfter</maml:name>
          <maml:Description>
            <maml:para>{{ Fill LinesAfter Description }}</maml:para>
          </maml:Description>
          <command:parameterValue required="true" variableLength="false">Int32</command:parameterValue>
          <dev:type>
            <maml:name>Int32</maml:name>
            <maml:uri />
          </dev:type>
          <dev:defaultValue>None</dev:defaultValue>
        </command:parameter>
        <command:parameter required="false" variableLength="true" globbing="false" pipelineInput="False" position="nommé" aliases="none">
          <maml:name>LinesBefore</maml:name>
          <maml:Description>
            <maml:para>{{ Fill LinesBefore Description }}</maml:para>
          </maml:Description>
          <command:parameterValue required="true" variableLength="false">Int32</command:parameterValue>
          <dev:type>
            <maml:name>Int32</maml:name>
            <maml:uri />
          </dev:type>
          <dev:defaultValue>None</dev:defaultValue>
        </command:parameter>
        <command:parameter required="false" variableLength="true" globbing="false" pipelineInput="True (ByValue)" position="nommé" aliases="none">
          <maml:name>LogFile</maml:name>
          <maml:Description>
            <maml:para>{{ Fill LogFile Description }}</maml:para>
          </maml:Description>
          <command:parameterValue required="true" variableLength="false">String</command:parameterValue>
          <dev:type>
            <maml:name>String</maml:name>
            <maml:uri />
          </dev:type>
          <dev:defaultValue>None</dev:defaultValue>
        </command:parameter>
        <command:parameter required="false" variableLength="true" globbing="false" pipelineInput="False" position="nommé" aliases="none">
          <maml:name>NoNewLine</maml:name>
          <maml:Description>
            <maml:para>{{ Fill NoNewLine Description }}</maml:para>
          </maml:Description>
          <dev:type>
            <maml:name>SwitchParameter</maml:name>
            <maml:uri />
          </dev:type>
          <dev:defaultValue>False</dev:defaultValue>
        </command:parameter>
        <command:parameter required="false" variableLength="true" globbing="false" pipelineInput="False" position="nommé" aliases="none">
          <maml:name>ShowTime</maml:name>
          <maml:Description>
            <maml:para>{{ Fill ShowTime Description }}</maml:para>
          </maml:Description>
          <dev:type>
            <maml:name>SwitchParameter</maml:name>
            <maml:uri />
          </dev:type>
          <dev:defaultValue>False</dev:defaultValue>
        </command:parameter>
        <command:parameter required="false" variableLength="true" globbing="false" pipelineInput="False" position="nommé" aliases="none">
          <maml:name>StartTab</maml:name>
          <maml:Description>
            <maml:para>{{ Fill StartTab Description }}</maml:para>
          </maml:Description>
          <command:parameterValue required="true" variableLength="false">Int32</command:parameterValue>
          <dev:type>
            <maml:name>Int32</maml:name>
            <maml:uri />
          </dev:type>
          <dev:defaultValue>None</dev:defaultValue>
        </command:parameter>
        <command:parameter required="true" variableLength="true" globbing="false" pipelineInput="True (ByValue)" position="nommé" aliases="none">
          <maml:name>Text</maml:name>
          <maml:Description>
            <maml:para>{{ Fill Text Description }}</maml:para>
          </maml:Description>
          <command:parameterValue required="true" variableLength="false">String[]</command:parameterValue>
          <dev:type>
            <maml:name>String[]</maml:name>
            <maml:uri />
          </dev:type>
          <dev:defaultValue>None</dev:defaultValue>
        </command:parameter>
      </command:syntaxItem>
    </command:syntax>
    <command:parameters>
      <command:parameter required="false" variableLength="true" globbing="false" pipelineInput="False" position="nommé" aliases="none">
        <maml:name>Color</maml:name>
        <maml:Description>
          <maml:para>{{ Fill Color Description }}</maml:para>
        </maml:Description>
        <command:parameterValue required="true" variableLength="false">ConsoleColor[]</command:parameterValue>
        <dev:type>
          <maml:name>ConsoleColor[]</maml:name>
          <maml:uri />
        </dev:type>
        <dev:defaultValue>None</dev:defaultValue>
      </command:parameter>
      <command:parameter required="true" variableLength="true" globbing="false" pipelineInput="True (ByValue)" position="nommé" aliases="none">
        <maml:name>EndLog</maml:name>
        <maml:Description>
          <maml:para>{{ Fill EndLog Description }}</maml:para>
        </maml:Description>
        <command:parameterValue required="false" variableLength="false">SwitchParameter</command:parameterValue>
        <dev:type>
          <maml:name>SwitchParameter</maml:name>
          <maml:uri />
        </dev:type>
        <dev:defaultValue>False</dev:defaultValue>
      </command:parameter>
      <command:parameter required="false" variableLength="true" globbing="false" pipelineInput="False" position="nommé" aliases="none">
        <maml:name>LinesAfter</maml:name>
        <maml:Description>
          <maml:para>{{ Fill LinesAfter Description }}</maml:para>
        </maml:Description>
        <command:parameterValue required="true" variableLength="false">Int32</command:parameterValue>
        <dev:type>
          <maml:name>Int32</maml:name>
          <maml:uri />
        </dev:type>
        <dev:defaultValue>None</dev:defaultValue>
      </command:parameter>
      <command:parameter required="false" variableLength="true" globbing="false" pipelineInput="False" position="nommé" aliases="none">
        <maml:name>LinesBefore</maml:name>
        <maml:Description>
          <maml:para>{{ Fill LinesBefore Description }}</maml:para>
        </maml:Description>
        <command:parameterValue required="true" variableLength="false">Int32</command:parameterValue>
        <dev:type>
          <maml:name>Int32</maml:name>
          <maml:uri />
        </dev:type>
        <dev:defaultValue>None</dev:defaultValue>
      </command:parameter>
      <command:parameter required="false" variableLength="true" globbing="false" pipelineInput="True (ByValue)" position="nommé" aliases="none">
        <maml:name>LogFile</maml:name>
        <maml:Description>
          <maml:para>{{ Fill LogFile Description }}</maml:para>
        </maml:Description>
        <command:parameterValue required="true" variableLength="false">String</command:parameterValue>
        <dev:type>
          <maml:name>String</maml:name>
          <maml:uri />
        </dev:type>
        <dev:defaultValue>None</dev:defaultValue>
      </command:parameter>
      <command:parameter required="false" variableLength="true" globbing="false" pipelineInput="False" position="nommé" aliases="none">
        <maml:name>NoNewLine</maml:name>
        <maml:Description>
          <maml:para>{{ Fill NoNewLine Description }}</maml:para>
        </maml:Description>
        <command:parameterValue required="false" variableLength="false">SwitchParameter</command:parameterValue>
        <dev:type>
          <maml:name>SwitchParameter</maml:name>
          <maml:uri />
        </dev:type>
        <dev:defaultValue>False</dev:defaultValue>
      </command:parameter>
      <command:parameter required="false" variableLength="true" globbing="false" pipelineInput="False" position="nommé" aliases="none">
        <maml:name>ShowTime</maml:name>
        <maml:Description>
          <maml:para>{{ Fill ShowTime Description }}</maml:para>
        </maml:Description>
        <command:parameterValue required="false" variableLength="false">SwitchParameter</command:parameterValue>
        <dev:type>
          <maml:name>SwitchParameter</maml:name>
          <maml:uri />
        </dev:type>
        <dev:defaultValue>False</dev:defaultValue>
      </command:parameter>
      <command:parameter required="true" variableLength="true" globbing="false" pipelineInput="True (ByValue)" position="nommé" aliases="none">
        <maml:name>StartLog</maml:name>
        <maml:Description>
          <maml:para>{{ Fill StartLog Description }}</maml:para>
        </maml:Description>
        <command:parameterValue required="false" variableLength="false">SwitchParameter</command:parameterValue>
        <dev:type>
          <maml:name>SwitchParameter</maml:name>
          <maml:uri />
        </dev:type>
        <dev:defaultValue>False</dev:defaultValue>
      </command:parameter>
      <command:parameter required="false" variableLength="true" globbing="false" pipelineInput="False" position="nommé" aliases="none">
        <maml:name>StartTab</maml:name>
        <maml:Description>
          <maml:para>{{ Fill StartTab Description }}</maml:para>
        </maml:Description>
        <command:parameterValue required="true" variableLength="false">Int32</command:parameterValue>
        <dev:type>
          <maml:name>Int32</maml:name>
          <maml:uri />
        </dev:type>
        <dev:defaultValue>None</dev:defaultValue>
      </command:parameter>
      <command:parameter required="true" variableLength="true" globbing="false" pipelineInput="True (ByValue)" position="nommé" aliases="none">
        <maml:name>Text</maml:name>
        <maml:Description>
          <maml:para>{{ Fill Text Description }}</maml:para>
        </maml:Description>
        <command:parameterValue required="true" variableLength="false">String[]</command:parameterValue>
        <dev:type>
          <maml:name>String[]</maml:name>
          <maml:uri />
        </dev:type>
        <dev:defaultValue>None</dev:defaultValue>
      </command:parameter>
    </command:parameters>
    <command:inputTypes>
      <command:inputType>
        <dev:type>
          <maml:name>System.String[]</maml:name>
        </dev:type>
        <maml:description>
          <maml:para></maml:para>
        </maml:description>
      </command:inputType>
      <command:inputType>
        <dev:type>
          <maml:name>System.Management.Automation.SwitchParameter</maml:name>
        </dev:type>
        <maml:description>
          <maml:para></maml:para>
        </maml:description>
      </command:inputType>
      <command:inputType>
        <dev:type>
          <maml:name>System.String</maml:name>
        </dev:type>
        <maml:description>
          <maml:para></maml:para>
        </maml:description>
      </command:inputType>
    </command:inputTypes>
    <command:returnValues>
      <command:returnValue>
        <dev:type>
          <maml:name>System.Object</maml:name>
        </dev:type>
        <maml:description>
          <maml:para></maml:para>
        </maml:description>
      </command:returnValue>
    </command:returnValues>
    <maml:alertSet>
      <maml:alert>
        <maml:para></maml:para>
      </maml:alert>
    </maml:alertSet>
    <command:examples>
      <command:example>
        <maml:title>-------------------------- Example 1 --------------------------</maml:title>
        <dev:code>PS C:\&gt; {{ Add example code here }}</dev:code>
        <dev:remarks>
          <maml:para>{{ Add example description here }}</maml:para>
        </dev:remarks>
      </command:example>
    </command:examples>
    <command:relatedLinks />
  </command:command>
  <command:command xmlns:maml="http://schemas.microsoft.com/maml/2004/10" xmlns:command="http://schemas.microsoft.com/maml/dev/command/2004/10" xmlns:dev="http://schemas.microsoft.com/maml/dev/2004/10" xmlns:MSHelp="http://msdn.microsoft.com/mshelp">
    <command:details>
      <command:name>Write-LineProgress</command:name>
      <command:verb>Write</command:verb>
      <command:noun>LineProgress</command:noun>
      <maml:description>
        <maml:para>Write Progress Bar in console</maml:para>
      </maml:description>
    </command:details>
    <maml:description>
      <maml:para>Write Progress Bar in console</maml:para>
    </maml:description>
    <command:syntax>
      <command:syntaxItem>
        <maml:name>Write-LineProgress</maml:name>
        <command:parameter required="true" variableLength="true" globbing="false" pipelineInput="False" position="1" aliases="none">
          <maml:name>Activity</maml:name>
          <maml:Description>
            <maml:para>{{ Fill Activity Description }}</maml:para>
          </maml:Description>
          <command:parameterValue required="true" variableLength="false">String</command:parameterValue>
          <dev:type>
            <maml:name>String</maml:name>
            <maml:uri />
          </dev:type>
          <dev:defaultValue>None</dev:defaultValue>
        </command:parameter>
        <command:parameter required="true" variableLength="true" globbing="false" pipelineInput="False" position="2" aliases="none">
          <maml:name>Progress</maml:name>
          <maml:Description>
            <maml:para>{{ Fill Progress Description }}</maml:para>
          </maml:Description>
          <command:parameterValue required="true" variableLength="false">Int32</command:parameterValue>
          <dev:type>
            <maml:name>Int32</maml:name>
            <maml:uri />
          </dev:type>
          <dev:defaultValue>0</dev:defaultValue>
        </command:parameter>
      </command:syntaxItem>
    </command:syntax>
    <command:parameters>
      <command:parameter required="true" variableLength="true" globbing="false" pipelineInput="False" position="1" aliases="none">
        <maml:name>Activity</maml:name>
        <maml:Description>
          <maml:para>{{ Fill Activity Description }}</maml:para>
        </maml:Description>
        <command:parameterValue required="true" variableLength="false">String</command:parameterValue>
        <dev:type>
          <maml:name>String</maml:name>
          <maml:uri />
        </dev:type>
        <dev:defaultValue>None</dev:defaultValue>
      </command:parameter>
      <command:parameter required="true" variableLength="true" globbing="false" pipelineInput="False" position="2" aliases="none">
        <maml:name>Progress</maml:name>
        <maml:Description>
          <maml:para>{{ Fill Progress Description }}</maml:para>
        </maml:Description>
        <command:parameterValue required="true" variableLength="false">Int32</command:parameterValue>
        <dev:type>
          <maml:name>Int32</maml:name>
          <maml:uri />
        </dev:type>
        <dev:defaultValue>0</dev:defaultValue>
      </command:parameter>
    </command:parameters>
    <command:inputTypes />
    <command:returnValues />
    <maml:alertSet>
      <maml:alert>
        <maml:para></maml:para>
      </maml:alert>
    </maml:alertSet>
    <command:examples>
      <command:example>
        <maml:title>-------------------------- EXEMPLE 1 --------------------------</maml:title>
        <dev:code>for ($i = 0; $i -lt 100; $i++) {</dev:code>
        <dev:remarks>
          <maml:para>Start-Sleep 1         Write-LineProgress -Activity "Test" -Progress $i         }</maml:para>
          <maml:para>Test [■■■■■■■■■■■----------------------------------------------------------------] 15%</maml:para>
        </dev:remarks>
      </command:example>
    </command:examples>
    <command:relatedLinks />
  </command:command>
  <command:command xmlns:maml="http://schemas.microsoft.com/maml/2004/10" xmlns:command="http://schemas.microsoft.com/maml/dev/command/2004/10" xmlns:dev="http://schemas.microsoft.com/maml/dev/2004/10" xmlns:MSHelp="http://msdn.microsoft.com/mshelp">
    <command:details>
      <command:name>Write-Menu</command:name>
      <command:verb>Write</command:verb>
      <command:noun>Menu</command:noun>
      <maml:description>
        <maml:para>{{ Fill in the Synopsis }}</maml:para>
      </maml:description>
    </command:details>
    <maml:description>
      <maml:para>{{ Fill in the Description }}</maml:para>
    </maml:description>
    <command:syntax>
      <command:syntaxItem>
        <maml:name>Write-Menu</maml:name>
        <command:parameter required="true" variableLength="true" globbing="false" pipelineInput="True (ByValue)" position="0" aliases="InputObject">
          <maml:name>Entries</maml:name>
          <maml:Description>
            <maml:para>{{ Fill Entries Description }}</maml:para>
          </maml:Description>
          <command:parameterValue required="true" variableLength="false">Object</command:parameterValue>
          <dev:type>
            <maml:name>Object</maml:name>
            <maml:uri />
          </dev:type>
          <dev:defaultValue>None</dev:defaultValue>
        </command:parameter>
        <command:parameter required="false" variableLength="true" globbing="false" pipelineInput="True (ByPropertyName)" position="1" aliases="Name">
          <maml:name>Title</maml:name>
          <maml:Description>
            <maml:para>{{ Fill Title Description }}</maml:para>
          </maml:Description>
          <command:parameterValue required="true" variableLength="false">String</command:parameterValue>
          <dev:type>
            <maml:name>String</maml:name>
            <maml:uri />
          </dev:type>
          <dev:defaultValue>None</dev:defaultValue>
        </command:parameter>
        <command:parameter required="false" variableLength="true" globbing="false" pipelineInput="False" position="nommé" aliases="none">
          <maml:name>MultiSelect</maml:name>
          <maml:Description>
            <maml:para>{{ Fill MultiSelect Description }}</maml:para>
          </maml:Description>
          <dev:type>
            <maml:name>SwitchParameter</maml:name>
            <maml:uri />
          </dev:type>
          <dev:defaultValue>False</dev:defaultValue>
        </command:parameter>
        <command:parameter required="false" variableLength="true" globbing="false" pipelineInput="False" position="nommé" aliases="none">
          <maml:name>Sort</maml:name>
          <maml:Description>
            <maml:para>{{ Fill Sort Description }}</maml:para>
          </maml:Description>
          <dev:type>
            <maml:name>SwitchParameter</maml:name>
            <maml:uri />
          </dev:type>
          <dev:defaultValue>False</dev:defaultValue>
        </command:parameter>
      </command:syntaxItem>
    </command:syntax>
    <command:parameters>
      <command:parameter required="true" variableLength="true" globbing="false" pipelineInput="True (ByValue)" position="0" aliases="InputObject">
        <maml:name>Entries</maml:name>
        <maml:Description>
          <maml:para>{{ Fill Entries Description }}</maml:para>
        </maml:Description>
        <command:parameterValue required="true" variableLength="false">Object</command:parameterValue>
        <dev:type>
          <maml:name>Object</maml:name>
          <maml:uri />
        </dev:type>
        <dev:defaultValue>None</dev:defaultValue>
      </command:parameter>
      <command:parameter required="false" variableLength="true" globbing="false" pipelineInput="False" position="nommé" aliases="none">
        <maml:name>MultiSelect</maml:name>
        <maml:Description>
          <maml:para>{{ Fill MultiSelect Description }}</maml:para>
        </maml:Description>
        <command:parameterValue required="false" variableLength="false">SwitchParameter</command:parameterValue>
        <dev:type>
          <maml:name>SwitchParameter</maml:name>
          <maml:uri />
        </dev:type>
        <dev:defaultValue>False</dev:defaultValue>
      </command:parameter>
      <command:parameter required="false" variableLength="true" globbing="false" pipelineInput="False" position="nommé" aliases="none">
        <maml:name>Sort</maml:name>
        <maml:Description>
          <maml:para>{{ Fill Sort Description }}</maml:para>
        </maml:Description>
        <command:parameterValue required="false" variableLength="false">SwitchParameter</command:parameterValue>
        <dev:type>
          <maml:name>SwitchParameter</maml:name>
          <maml:uri />
        </dev:type>
        <dev:defaultValue>False</dev:defaultValue>
      </command:parameter>
      <command:parameter required="false" variableLength="true" globbing="false" pipelineInput="True (ByPropertyName)" position="1" aliases="Name">
        <maml:name>Title</maml:name>
        <maml:Description>
          <maml:para>{{ Fill Title Description }}</maml:para>
        </maml:Description>
        <command:parameterValue required="true" variableLength="false">String</command:parameterValue>
        <dev:type>
          <maml:name>String</maml:name>
          <maml:uri />
        </dev:type>
        <dev:defaultValue>None</dev:defaultValue>
      </command:parameter>
    </command:parameters>
    <command:inputTypes>
      <command:inputType>
        <dev:type>
          <maml:name>System.Object</maml:name>
        </dev:type>
        <maml:description>
          <maml:para></maml:para>
        </maml:description>
      </command:inputType>
      <command:inputType>
        <dev:type>
          <maml:name>System.String</maml:name>
        </dev:type>
        <maml:description>
          <maml:para></maml:para>
        </maml:description>
      </command:inputType>
    </command:inputTypes>
    <command:returnValues>
      <command:returnValue>
        <dev:type>
          <maml:name>System.Object</maml:name>
        </dev:type>
        <maml:description>
          <maml:para></maml:para>
        </maml:description>
      </command:returnValue>
    </command:returnValues>
    <maml:alertSet>
      <maml:alert>
        <maml:para></maml:para>
      </maml:alert>
    </maml:alertSet>
    <command:examples>
      <command:example>
        <maml:title>-------------------------- Example 1 --------------------------</maml:title>
        <dev:code>PS C:\&gt; {{ Add example code here }}</dev:code>
        <dev:remarks>
          <maml:para>{{ Add example description here }}</maml:para>
        </dev:remarks>
      </command:example>
    </command:examples>
    <command:relatedLinks />
  </command:command>
  <command:command xmlns:maml="http://schemas.microsoft.com/maml/2004/10" xmlns:command="http://schemas.microsoft.com/maml/dev/command/2004/10" xmlns:dev="http://schemas.microsoft.com/maml/dev/2004/10" xmlns:MSHelp="http://msdn.microsoft.com/mshelp">
    <command:details>
      <command:name>Write-Title</command:name>
      <command:verb>Write</command:verb>
      <command:noun>Title</command:noun>
      <maml:description>
        <maml:para>Show a Title bar in Console</maml:para>
      </maml:description>
    </command:details>
    <maml:description>
      <maml:para>Show a Title bar in Console</maml:para>
    </maml:description>
    <command:syntax>
      <command:syntaxItem>
        <maml:name>Write-Title</maml:name>
        <command:parameter required="false" variableLength="true" globbing="false" pipelineInput="False" position="1" aliases="none">
          <maml:name>Message</maml:name>
          <maml:Description>
            <maml:para>{{ Fill Message Description }}</maml:para>
          </maml:Description>
          <command:parameterValue required="true" variableLength="false">Object</command:parameterValue>
          <dev:type>
            <maml:name>Object</maml:name>
            <maml:uri />
          </dev:type>
          <dev:defaultValue>None</dev:defaultValue>
        </command:parameter>
        <command:parameter required="false" variableLength="true" globbing="false" pipelineInput="False" position="2" aliases="none">
          <maml:name>Color</maml:name>
          <maml:Description>
            <maml:para>{{ Fill Color Description }}</maml:para>
          </maml:Description>
          <command:parameterValue required="true" variableLength="false">Object</command:parameterValue>
          <dev:type>
            <maml:name>Object</maml:name>
            <maml:uri />
          </dev:type>
          <dev:defaultValue>White</dev:defaultValue>
        </command:parameter>
        <command:parameter required="false" variableLength="true" globbing="false" pipelineInput="False" position="named" aliases="none">
          <maml:name>Upper</maml:name>
          <maml:Description>
            <maml:para>{{ Fill Upper Description }}</maml:para>
          </maml:Description>
          <dev:type>
            <maml:name>SwitchParameter</maml:name>
            <maml:uri />
          </dev:type>
          <dev:defaultValue>False</dev:defaultValue>
        </command:parameter>
      </command:syntaxItem>
    </command:syntax>
    <command:parameters>
      <command:parameter required="false" variableLength="true" globbing="false" pipelineInput="False" position="1" aliases="none">
        <maml:name>Message</maml:name>
        <maml:Description>
          <maml:para>{{ Fill Message Description }}</maml:para>
        </maml:Description>
        <command:parameterValue required="true" variableLength="false">Object</command:parameterValue>
        <dev:type>
          <maml:name>Object</maml:name>
          <maml:uri />
        </dev:type>
        <dev:defaultValue>None</dev:defaultValue>
      </command:parameter>
      <command:parameter required="false" variableLength="true" globbing="false" pipelineInput="False" position="2" aliases="none">
        <maml:name>Color</maml:name>
        <maml:Description>
          <maml:para>{{ Fill Color Description }}</maml:para>
        </maml:Description>
        <command:parameterValue required="true" variableLength="false">Object</command:parameterValue>
        <dev:type>
          <maml:name>Object</maml:name>
          <maml:uri />
        </dev:type>
        <dev:defaultValue>White</dev:defaultValue>
      </command:parameter>
      <command:parameter required="false" variableLength="true" globbing="false" pipelineInput="False" position="named" aliases="none">
        <maml:name>Upper</maml:name>
        <maml:Description>
          <maml:para>{{ Fill Upper Description }}</maml:para>
        </maml:Description>
        <command:parameterValue required="false" variableLength="false">SwitchParameter</command:parameterValue>
        <dev:type>
          <maml:name>SwitchParameter</maml:name>
          <maml:uri />
        </dev:type>
        <dev:defaultValue>False</dev:defaultValue>
      </command:parameter>
    </command:parameters>
    <command:inputTypes />
    <command:returnValues />
    <maml:alertSet>
      <maml:alert>
        <maml:para></maml:para>
      </maml:alert>
    </maml:alertSet>
    <command:examples>
      <command:example>
        <maml:title>-------------------------- EXEMPLE 1 --------------------------</maml:title>
        <dev:code>Write-Title -Message "Script de création d'utilisateur" -Upper -Color Red</dev:code>
        <dev:remarks>
          <maml:para>┌────────────────────────────────────────────────────────────────────────────────────────────────────────────────────────────────────────────┐ │                                                      SCRIPT DE CRÉATION D'UTILISATEUR                                                      │ └────────────────────────────────────────────────────────────────────────────────────────────────────────────────────────────────────────────┘</maml:para>
        </dev:remarks>
      </command:example>
    </command:examples>
    <command:relatedLinks />
  </command:command>
</helpItems>